crawlab/__init__.py
crawlab/cli/__init__.py
crawlab/config/__init__.py
crawlab/constants/__init__.py
crawlab/core/__init__.py
crawlab/core/client.py
crawlab/core/config.py
crawlab/core/log.py
crawlab/core/request.py
crawlab/db/__init__.py
crawlab/db/es.py
crawlab/db/kafka.py
crawlab/db/mongo.py
crawlab/db/sql.py
crawlab/pipelines/__init__.py
crawlab/utils/__init__.py
crawlab/utils/config.py
crawlab/utils/data.py
crawlab/utils/scrapy.py
test_crawlab_sdk-0.4.3.dist-info/METADATA
test_crawlab_sdk-0.4.3.dist-info/WHEEL
test_crawlab_sdk-0.4.3.dist-info/entry_points.txt
test_crawlab_sdk-0.4.3.dist-info/top_level.txt
test_crawlab_sdk-0.4.3.dist-info/RECORD
