Metadata-Version: 2.1
Name: test-crawlab-sdk
Version: 0.4.3
Summary: Python SDK for Crawlab
Home-page: UNKNOWN
Author: hzy
Author-email: 599012428@qq.com
License: BSD-3-Clause
Platform: UNKNOWN
Classifier: Programming Language :: Python :: 3
Classifier: License :: OSI Approved :: BSD License
Classifier: Operating System :: OS Independent
Requires-Dist: Click (==7.0)
Requires-Dist: requests (==2.22.0)
Requires-Dist: prettytable (==0.7.2)
Requires-Dist: scrapy (==2.2.0)
Requires-Dist: pymongo (==3.10.1)
Requires-Dist: pymysql (==0.9.3)
Requires-Dist: psycopg2-binary (==2.8.5)
Requires-Dist: kafka-python (==2.0.1)
Requires-Dist: elasticsearch (==7.8.0)
Requires-Dist: pathspec (==0.8.0)
